lazysloth/__init__.py
lazysloth/immutable_types.py
lazysloth/lazy_types.py
lazysloth-0.0.6.dist-info/METADATA
lazysloth-0.0.6.dist-info/WHEEL
lazysloth-0.0.6.dist-info/top_level.txt
lazysloth-0.0.6.dist-info/RECORD
