Metadata-Version: 2.1
Name: lazysloth
Version: 0.0.6
Summary: A Python library for lazy and immutable variables.
Author-email: Omer Holzinger <omer@omerholz.com>
Project-URL: Homepage, https://github.com/omerholz/lazysloth
Project-URL: Repository, https://github.com/omerholz/lazysloth
Keywords: lazy,immutable,variables
Classifier: Programming Language :: Python :: 3
Classifier: License :: OSI Approved :: MIT License
Classifier: Operating System :: OS Independent
Requires-Python: >=3.10
